red_dragon/__init__.py
red_dragon/cli.py
red_dragon-0.1.1.dist-info/licenses/LICENSE
red_dragon-0.1.1.dist-info/METADATA
red_dragon-0.1.1.dist-info/WHEEL
red_dragon-0.1.1.dist-info/entry_points.txt
red_dragon-0.1.1.dist-info/top_level.txt
red_dragon-0.1.1.dist-info/RECORD
