Metadata-Version: 2.4
Name: red-dragon
Version: 0.1.1
Summary: A Python package that awakens the red dragon
Author-email: karzimeg <your.email@example.com>
Keywords: dragon,cli,ascii-art
Classifier: Programming Language :: Python :: 3
Classifier: License :: OSI Approved :: MIT License
Classifier: Operating System :: OS Independent
Requires-Python: >=3.7
License-File: LICENSE
Dynamic: license-file
